delimited2fixedwidth.py
delimited2fixedwidth-1.0.11.dist-info/LICENSE
delimited2fixedwidth-1.0.11.dist-info/METADATA
delimited2fixedwidth-1.0.11.dist-info/WHEEL
delimited2fixedwidth-1.0.11.dist-info/top_level.txt
delimited2fixedwidth-1.0.11.dist-info/RECORD
