Metadata-Version: 2.1
Name: delimited2fixedwidth
Version: 1.0.11
Summary: Convert files from delimited (e.g. CSV) to fixed width format
Home-page: https://github.com/e2jk/delimited2fixedwidth
Author: Emilien Klein
Author-email: emilien@klein.st
License: UNKNOWN
Platform: UNKNOWN
Classifier: Programming Language :: Python :: 3
Classifier: License :: OSI Approved :: MIT License
Classifier: Operating System :: OS Independent
Requires-Python: >=3.6
Requires-Dist: openpyxl (==3.0.7)
Requires-Dist: et-xmlfile (==1.1.0) ; python_version >= "3.6"
